pyDOS/__init__.py
pyDOS/pathdict.py
pyDOS/run.py
pyDOS-0.0.1.dist-info/LICENSE
pyDOS-0.0.1.dist-info/METADATA
pyDOS-0.0.1.dist-info/WHEEL
pyDOS-0.0.1.dist-info/top_level.txt
pyDOS-0.0.1.dist-info/RECORD
