Metadata-Version: 2.1
Name: pyDOS
Version: 0.0.1
Summary: MSDOS-like environment in python
Home-page: https://github.com/Creeper-100/pyDOS
Author: Felix Bitsch
Author-email: felix.a.bitsch@gmail.com
License: UNKNOWN
Project-URL: Bug Tracker, https://github.com/Creeper-100/pyDOS/issues
Platform: UNKNOWN
Classifier: Development Status :: 3 - Alpha
Classifier: License :: OSI Approved :: MIT License
Classifier: Programming Language :: Python :: 3
Classifier: Programming Language :: Python :: 3.7
Classifier: Programming Language :: Python :: 3.8
Classifier: Programming Language :: Python :: 3.9
Requires-Python: >=3.7
